preferredsoundplayer/__init__.py
preferredsoundplayer/preferredsoundplayer.py
preferredsoundplayer-0.0.5.dist-info/LICENSE
preferredsoundplayer-0.0.5.dist-info/METADATA
preferredsoundplayer-0.0.5.dist-info/WHEEL
preferredsoundplayer-0.0.5.dist-info/top_level.txt
preferredsoundplayer-0.0.5.dist-info/RECORD
