Metadata-Version: 2.1
Name: preferredsoundplayer
Version: 0.0.5
Summary: I wanted a dependable sound player which is easy to implement, so I made and prefer this one.
Home-page: https://github.com/garydavenport73/PreferredSoundPlayer
Author: Gary Davenport
Author-email: dovedweller@gmail.com
License: UNKNOWN
Project-URL: Bug Tracker, https://github.com/garydavenport73/PreferredSoundPlayer/issues
Platform: UNKNOWN
Classifier: Programming Language :: Python :: 3
Classifier: License :: OSI Approved :: MIT License
Classifier: Operating System :: OS Independent
Requires-Python: >=3.6
License-File: LICENSE
